accli/AcceleratorJobProjectService.py
accli/AcceleratorTaskDispatcher.py
accli/AcceleratorTerminalCliProjectService.py
accli/CsvRegionalTimeseriesValidator.py
accli/__init__.py
accli/__main__.py
accli/_version.py
accli/cli.py
accli/common.py
accli/token.py
accli-1.0.3.dist-info/licenses/LICENSE
accli-1.0.3.dist-info/METADATA
accli-1.0.3.dist-info/WHEEL
accli-1.0.3.dist-info/entry_points.txt
accli-1.0.3.dist-info/top_level.txt
accli-1.0.3.dist-info/RECORD
