Metadata-Version: 2.4
Name: accli
Version: 1.0.3
Summary: IIASA Accelerator Client
Author-email: Wrufesh S <wrufesh@gmail.com>
License: The MIT License (MIT)
Project-URL: Homepage, https://github.com/iiasa/accli
Project-URL: Bug Tracker, https://github.com/iiasa/accli/issues
Classifier: Programming Language :: Python :: 3
Classifier: License :: OSI Approved :: MIT License
Classifier: Operating System :: OS Independent
Requires-Python: >=3.7
License-File: LICENSE
Requires-Dist: urllib3>=1.26.5
Requires-Dist: typer[all]>=0.4.0
Requires-Dist: tinydb>=4.5.2
Requires-Dist: requests>=2.25.1
Requires-Dist: jsonschema>=4.5.1
Requires-Dist: pydantic>=2.0
Dynamic: license-file
